Workbook

Sheet Anleitung
A1: 🏭 Factory Business Simulation - Spielanleitung
A2: Planspiel BWL für BDE - WiSe 2025/26
A4: 📋 Spielziel
B5: Führen Sie Ihre Fabrik ein Jahr lang (4 Quartale) und maximieren Sie den Gewinn.
A7: 🎮 Wie zu spielen
A8: 1. | B8: Gehen Sie zu 'Quartal 1' Tabellenblatt
A9: 2. | B9: Geben Sie Ihre Entscheidungen in GELB markierte Felder ein:
B10: • Verkaufspreis (M pro Einheit)
B11: • Marketing-Budget (M)
B12: • Produktionsmenge (Lose)
B13: • Materialpreis-Faktor (1.0 = normal)
A14: 3. | B14: Ergebnisse werden automatisch in GRÜNEN Feldern berechnet
A15: 4. | B15: Wiederholen Sie für Quartale 2, 3 und 4
A16: 5. | B16: Prüfen Sie 'Jahresabschluss' für Gesamtergebnis
A18: 💡 Entscheidungen
A19: Verkaufspreis: | B19: Höher = mehr Gewinn/Einheit, ABER weniger Nachfrage
A20: Marketing: | B20: Mehr Budget = höhere Nachfrage
A21: Produktion: | B21: Mehr Lose = können mehr verkaufen (wenn Nachfrage da ist)
A22: Materialfaktor: | B22: Simuliert Marktpreisschwankungen
A24: 📊 Anfangsbestand
A25: Kasse: | B25: 28.0 M
A26: Forderungen: | B26: 26.0 M
A27: Rohmaterial: | B27: 2 Lose
A28: Halbfertigware: | B28: 2 Lose
A29: Fertigware: | B29: 2 Lose
A31: 🎯 Erfolgsbewertung
A32: Sehr gut: | B32: Nettogewinn > 30 M, Umsatzrendite > 20%
A33: Gut: | B33: Nettogewinn 15-30 M, Umsatzrendite 10-20%
A34: Befriedigend: | B34: Nettogewinn 5-15 M, Umsatzrendite 5-10%

Sheet Parameter
A1: Parameter | B1: Wert | C1: Einheit
A2: Basis Verkaufspreis | B2: 13 | C2: M/Einheit
A3: Basis Materialpreis | B3: 3 | C3: M/Los
A4: Basis Fertigungskosten | B4: 3 | C4: M/Los
A5: Basis Montagekosten | B5: 1 | C5: M/Los
A6: Basis Gemeinkosten | B6: 6 | C6: M/Quartal
A7: Preiselastizität | B7: 0.15 | C7: Faktor
A8: Marketing-Effektivität | B8: 0.08 | C8: Faktor

Sheet Quartal 1
A1: Quartal 1
A3: 📝 IHRE ENTSCHEIDUNGEN (Gelb = Eingabe)
A4: Verkaufspreis (M/Einheit)
A5: Marketing-Budget (M) | B5: 13
A6: Produktionsmenge (Lose) | B6: 0
A7: Materialpreis-Faktor | B7: 2
B8: 1
A10: 📊 ERGEBNISSE (Grün = Automatisch berechnet)
A11: Nachfrage (Lose)
A12: Absatz (Lose) | B12: =2
A13: Umsatz (M) | B13: =MIN(B12,2)
A14: Materialkosten (M) | B14: =B5*B13
A15: Fertigungskosten (M) | B15: =3*B7*B8
A16: Montagekosten (M) | B16: =3*B7
A17: Gemeinkosten (M) | B17: =1*B7
A18: Marketingkosten (M) | B18: =6
A19: Gesamtkosten (M) | B19: =B6
A20: Nettogewinn (M) | B20: =SUM(B15:B19)
B21: =B14-B20
A23: 💰 CASH FLOW
A24: Kasse Anfang
A25: Kasse Ende | B25: 28
B26: =B25+26-B20

Sheet Quartal 2
A1: Quartal 2
A3: 📝 IHRE ENTSCHEIDUNGEN (Gelb = Eingabe)
A4: Verkaufspreis (M/Einheit)
A5: Marketing-Budget (M) | B5: 13
A6: Produktionsmenge (Lose) | B6: 0
A7: Materialpreis-Faktor | B7: 2
B8: 1
A10: 📊 ERGEBNISSE (Grün = Automatisch berechnet)
A11: Nachfrage (Lose)
A12: Absatz (Lose) | B12: =2
A13: Umsatz (M) | B13: =MIN(B12,2)
A14: Materialkosten (M) | B14: =B5*B13
A15: Fertigungskosten (M) | B15: =3*B7*B8
A16: Montagekosten (M) | B16: =3*B7
A17: Gemeinkosten (M) | B17: =1*B7
A18: Marketingkosten (M) | B18: =6
A19: Gesamtkosten (M) | B19: =B6
A20: Nettogewinn (M) | B20: =SUM(B15:B19)
B21: =B14-B20
A23: 💰 CASH FLOW
A24: Kasse Anfang
A25: Kasse Ende | B25: ='Quartal 1'!B26
B26: =B25+26-B20

Sheet Quartal 3
A1: Quartal 3
A3: 📝 IHRE ENTSCHEIDUNGEN (Gelb = Eingabe)
A4: Verkaufspreis (M/Einheit)
A5: Marketing-Budget (M) | B5: 13
A6: Produktionsmenge (Lose) | B6: 0
A7: Materialpreis-Faktor | B7: 2
B8: 1
A10: 📊 ERGEBNISSE (Grün = Automatisch berechnet)
A11: Nachfrage (Lose)
A12: Absatz (Lose) | B12: =2
A13: Umsatz (M) | B13: =MIN(B12,2)
A14: Materialkosten (M) | B14: =B5*B13
A15: Fertigungskosten (M) | B15: =3*B7*B8
A16: Montagekosten (M) | B16: =3*B7
A17: Gemeinkosten (M) | B17: =1*B7
A18: Marketingkosten (M) | B18: =6
A19: Gesamtkosten (M) | B19: =B6
A20: Nettogewinn (M) | B20: =SUM(B15:B19)
B21: =B14-B20
A23: 💰 CASH FLOW
A24: Kasse Anfang
A25: Kasse Ende | B25: ='Quartal 2'!B26
B26: =B25+26-B20

Sheet Quartal 4
A1: Quartal 4
A3: 📝 IHRE ENTSCHEIDUNGEN (Gelb = Eingabe)
A4: Verkaufspreis (M/Einheit)
A5: Marketing-Budget (M) | B5: 13
A6: Produktionsmenge (Lose) | B6: 0
A7: Materialpreis-Faktor | B7: 2
B8: 1
A10: 📊 ERGEBNISSE (Grün = Automatisch berechnet)
A11: Nachfrage (Lose)
A12: Absatz (Lose) | B12: =2
A13: Umsatz (M) | B13: =MIN(B12,2)
A14: Materialkosten (M) | B14: =B5*B13
A15: Fertigungskosten (M) | B15: =3*B7*B8
A16: Montagekosten (M) | B16: =3*B7
A17: Gemeinkosten (M) | B17: =1*B7
A18: Marketingkosten (M) | B18: =6
A19: Gesamtkosten (M) | B19: =B6
A20: Nettogewinn (M) | B20: =SUM(B15:B19)
B21: =B14-B20
A23: 💰 CASH FLOW
A24: Kasse Anfang
A25: Kasse Ende | B25: ='Quartal 3'!B26
B26: =B25+26-B20

Sheet Jahresabschluss
A1: 📈 Jahresabschluss - Zusammenfassung
A3: Kennzahl | B3: Wert
A4: Gesamtumsatz | B4: =SUM('Quartal 1'!B14,'Quartal 2'!B14,'Quartal 3'!B14,'Quartal 4'!B14)
A5: Gesamtkosten | B5: =SUM('Quartal 1'!B20,'Quartal 2'!B20,'Quartal 3'!B20,'Quartal 4'!B20)
A6: Gesamtgewinn | B6: =B4-B5
A7: Durchschn. Gewinn/Quartal | B7: =B6/4
A8: Endbestand Kasse | B8: ='Quartal 4'!B26
A9: Umsatzrendite (%) | B9: =IF(B4>0,B6/B4*100,0)
A12: Quartalsentwicklung
A13: Quartal | B13: Umsatz | C13: Kosten | D13: Gewinn
A14: Q1 | B14: ='Quartal 1'!B14 | C14: ='Quartal 1'!B20 | D14: ='Quartal 1'!B21
A15: Q2 | B15: ='Quartal 2'!B14 | C15: ='Quartal 2'!B20 | D15: ='Quartal 2'!B21
A16: Q3 | B16: ='Quartal 3'!B14 | C16: ='Quartal 3'!B20 | D16: ='Quartal 3'!B21
A17: Q4 | B17: ='Quartal 4'!B14 | C17: ='Quartal 4'!B20 | D17: ='Quartal 4'!B21
