Workbook

Sheet Parameter
A1: SPIELPARAMETER
A3: Parameter | B3: Wert | C3: Einheit
A4: Basis Verkaufspreis | B4: 13 | C4: M/Einheit
A5: Basis Materialpreis | B5: 3 | C5: M/Los
A6: Basis Fertigungskosten | B6: 3 | C6: M/Los
A7: Basis Montagekosten | B7: 1 | C7: M/Los
A8: Basis Gemeinkosten | B8: 6 | C8: M/Quartal
A10: Marktparameter
A11: Basis Nachfrage | B11: 2 | C11: Lose/Quartal
A12: Preiselastizität | B12: 0.15
A13: Marketing-Effektivität | B13: 0.08
A14: Wettbewerberpreis | B14: 12.5 | C14: M/Einheit

Sheet Quartal 1
A1: QUARTAL 1
A3: ANFANGSBESTAND
A4: Kasse | B4: 28
A5: Forderungen | B5: 26
A6: Rohmaterial (Lose) | B6: 2
A7: Halbfertigware (Lose) | B7: 2
A8: Fertigware (Lose) | B8: 2
A10: IHRE ENTSCHEIDUNGEN
A11: Verkaufspreis (M/Einheit) | B11: 13
A12: Marketing-Budget (M) | B12: 0
A13: Produktionsmenge (Lose) | B13: 2
A14: Materialpreis-Faktor | B14: 1
A16: BERECHNUNGEN
A17: Nachfrage (berechnet, Lose) | B17: =MAX(1, ROUND(Parameter!$B$11 * (1 - (B11/Parameter!$B$4 - 1) * Parameter!$B$12) * (1 + B12 * Parameter!$B$13), 0))
A18: Verkaufsmenge (Lose) | B18: =MIN(B17, B8)
A19: Umsatz (M) | B19: =B18 * B11
A21: KOSTEN
A22: Materialkosten (M) | B22: =2 * Parameter!$B$5 * B14
A23: Fertigungskosten (M) | B23: =B13 * Parameter!$B$6
A24: Montagekosten (M) | B24: =B13 * Parameter!$B$7
A25: Gemeinkosten (M) | B25: =Parameter!$B$8
A26: Marketing (M) | B26: =B12
A27: Gesamtkosten (M) | B27: =SUM(B22:B26)
A29: ERGEBNIS
A30: Bruttogewinn (M) | B30: =B19 - (B22 + B23 + B24)
A31: Nettogewinn (M) | B31: =B19 - B27
A33: ENDBESTAND
A34: Kasse (M) | B34: =B4 + B5 - B27
A35: Forderungen (M) | B35: =B19
A36: Rohmaterial (Lose) | B36: =B6 + 2 - B13
A37: Halbfertigware (Lose) | B37: =B7 + B13 - B13
A38: Fertigware (Lose) | B38: =B8 + B13 - B18

Sheet Quartal 2
A1: QUARTAL 2
A3: ANFANGSBESTAND
A4: Kasse | B4: ='Quartal 1'!B34
A5: Forderungen | B5: ='Quartal 1'!B35
A6: Rohmaterial (Lose) | B6: ='Quartal 1'!B36
A7: Halbfertigware (Lose) | B7: ='Quartal 1'!B37
A8: Fertigware (Lose) | B8: 'Quartal 1'!B38
A10: IHRE ENTSCHEIDUNGEN
A11: Verkaufspreis (M/Einheit) | B11: 13
A12: Marketing-Budget (M) | B12: 0
A13: Produktionsmenge (Lose) | B13: 2
A14: Materialpreis-Faktor | B14: 1
A16: BERECHNUNGEN
A17: Nachfrage (berechnet, Lose) | B17: =MAX(1, ROUND(Parameter!$B$11 * (1 - (B11/Parameter!$B$4 - 1) * Parameter!$B$12) * (1 + B12 * Parameter!$B$13), 0))
A18: Verkaufsmenge (Lose) | B18: =MIN(B17, B8)
A19: Umsatz (M) | B19: =B18 * B11
A21: KOSTEN
A22: Materialkosten (M) | B22: =2 * Parameter!$B$5 * B14
A23: Fertigungskosten (M) | B23: =B13 * Parameter!$B$6
A24: Montagekosten (M) | B24: =B13 * Parameter!$B$7
A25: Gemeinkosten (M) | B25: =Parameter!$B$8
A26: Marketing (M) | B26: =B12
A27: Gesamtkosten (M) | B27: =SUM(B22:B26)
A29: ERGEBNIS
A30: Bruttogewinn (M) | B30: =B19 - (B22 + B23 + B24)
A31: Nettogewinn (M) | B31: =B19 - B27
A33: ENDBESTAND
A34: Kasse (M) | B34: =B4 + B5 - B27
A35: Forderungen (M) | B35: =B19
A36: Rohmaterial (Lose) | B36: =B6 + 2 - B13
A37: Halbfertigware (Lose) | B37: =B7 + B13 - B13
A38: Fertigware (Lose) | B38: =B8 + B13 - B18

Sheet Quartal 3
A1: QUARTAL 3
A3: ANFANGSBESTAND
A4: Kasse | B4: ='Quartal 2'!B34
A5: Forderungen | B5: 'Quartal 2'!B35
A6: Rohmaterial (Lose) | B6: 'Quartal 2'!B36
A7: Halbfertigware (Lose) | B7: 'Quartal 2'!B37
A8: Fertigware (Lose) | B8: 'Quartal 2'!B38
A10: IHRE ENTSCHEIDUNGEN
A11: Verkaufspreis (M/Einheit) | B11: 13
A12: Marketing-Budget (M) | B12: 0
A13: Produktionsmenge (Lose) | B13: 2
A14: Materialpreis-Faktor | B14: 1
A16: BERECHNUNGEN
A17: Nachfrage (berechnet, Lose) | B17: =MAX(1, ROUND(Parameter!$B$11 * (1 - (B11/Parameter!$B$4 - 1) * Parameter!$B$12) * (1 + B12 * Parameter!$B$13), 0))
A18: Verkaufsmenge (Lose) | B18: =MIN(B17, B8)
A19: Umsatz (M) | B19: =B18 * B11
A21: KOSTEN
A22: Materialkosten (M) | B22: =2 * Parameter!$B$5 * B14
A23: Fertigungskosten (M) | B23: =B13 * Parameter!$B$6
A24: Montagekosten (M) | B24: =B13 * Parameter!$B$7
A25: Gemeinkosten (M) | B25: =Parameter!$B$8
A26: Marketing (M) | B26: =B12
A27: Gesamtkosten (M) | B27: =SUM(B22:B26)
A29: ERGEBNIS
A30: Bruttogewinn (M) | B30: =B19 - (B22 + B23 + B24)
A31: Nettogewinn (M) | B31: =B19 - B27
A33: ENDBESTAND
A34: Kasse (M) | B34: =B4 + B5 - B27
A35: Forderungen (M) | B35: =B19
A36: Rohmaterial (Lose) | B36: =B6 + 2 - B13
A37: Halbfertigware (Lose) | B37: =B7 + B13 - B13
A38: Fertigware (Lose) | B38: =B8 + B13 - B18

Sheet Quartal 4
A1: QUARTAL 4
A3: ANFANGSBESTAND
A4: Kasse | B4: ='Quartal 3'!B34
A5: Forderungen | B5: 'Quartal 3'!B35
A6: Rohmaterial (Lose) | B6: 'Quartal 3'!B36
A7: Halbfertigware (Lose) | B7: 'Quartal 3'!B37
A8: Fertigware (Lose) | B8: 'Quartal 3'!B38
A10: IHRE ENTSCHEIDUNGEN
A11: Verkaufspreis (M/Einheit) | B11: 13
A12: Marketing-Budget (M) | B12: 0
A13: Produktionsmenge (Lose) | B13: 2
A14: Materialpreis-Faktor | B14: 1
A16: BERECHNUNGEN
A17: Nachfrage (berechnet, Lose) | B17: =MAX(1, ROUND(Parameter!$B$11 * (1 - (B11/Parameter!$B$4 - 1) * Parameter!$B$12) * (1 + B12 * Parameter!$B$13), 0))
A18: Verkaufsmenge (Lose) | B18: =MIN(B17, B8)
A19: Umsatz (M) | B19: =B18 * B11
A21: KOSTEN
A22: Materialkosten (M) | B22: =2 * Parameter!$B$5 * B14
A23: Fertigungskosten (M) | B23: =B13 * Parameter!$B$6
A24: Montagekosten (M) | B24: =B13 * Parameter!$B$7
A25: Gemeinkosten (M) | B25: =Parameter!$B$8
A26: Marketing (M) | B26: =B12
A27: Gesamtkosten (M) | B27: =SUM(B22:B26)
A29: ERGEBNIS
A30: Bruttogewinn (M) | B30: =B19 - (B22 + B23 + B24)
A31: Nettogewinn (M) | B31: =B19 - B27
A33: ENDBESTAND
A34: Kasse (M) | B34: =B4 + B5 - B27
A35: Forderungen (M) | B35: =B19
A36: Rohmaterial (Lose) | B36: =B6 + 2 - B13
A37: Halbfertigware (Lose) | B37: =B7 + B13 - B13
A38: Fertigware (Lose) | B38: =B8 + B13 - B18

Sheet Jahresabschluss
A1: JAHRESABSCHLUSS
A3: Quartal | B3: Umsatz (M) | C3: Kosten (M) | D3: Gewinn (M)
A4: 1 | B4: ='Quartal 1'!B19 | C4: ='Quartal 1'!B27 | D4: ='Quartal 1'!B31
A5: 2 | B5: ='Quartal 2'!B19 | C5: ='Quartal 2'!B27 | D5: ='Quartal 2'!B31
A6: 3 | B6: ='Quartal 3'!B19 | C6: ='Quartal 3'!B27 | D6: ='Quartal 3'!B31
A7: 4 | B7: ='Quartal 4'!B19 | C7: ='Quartal 4'!B27 | D7: ='Quartal 4'!B31
A8: GESAMT | B8: =SUM(B4:B7) | C8: =SUM(C4:C7) | D8: =SUM(D4:D7)
A10: KENNZAHLEN
A11: Durchschn. Gewinn/Quartal | B11: =D8/4
A12: Umsatzrendite (%) | B12: =IF(B8>0, D8/B8*100, 0)
A13: Endbestand Kasse | B13: ='Quartal 4'!B34

Sheet Anleitung
A1: FACTORY BUSINESS SIMULATION - ANLEITUNG
A2: Planspiel BWL für BDE - WiSe 2025/26
A4: SPIELABLAUF:
A5: 1. Öffnen Sie das 'Parameter' Tabellenblatt und überprüfen Sie die Grundeinstellungen.
A6: 2. Gehen Sie zu 'Quartal 1' und geben Sie Ihre Entscheidungen ein (gelb markierte Felder):
A7: - Verkaufspreis
A8: - Marketing-Budget
A9: - Produktionsmenge
A10: - Materialpreis-Faktor (z.B. 1.1 = 10% Preissteigerung)
A11: 3. Die Ergebnisse werden automatisch berechnet (grün markierte Felder).
A12: 4. Wiederholen Sie Schritt 2-3 für Quartale 2, 3 und 4.
A13: 5. Sehen Sie sich den 'Jahresabschluss' an für die Gesamtübersicht.
... A29: Maximieren Sie den Gewinn über 4 Quartale durch geschickte Preis-, Produktions- und Marketingentscheidungen!
